README.md
setup.cfg
setup.py
CLUSTER_SELECTION/__init__.py
CLUSTER_SELECTION/cluster_selection.py
CLUSTER_SELECTION.egg-info/PKG-INFO
CLUSTER_SELECTION.egg-info/SOURCES.txt
CLUSTER_SELECTION.egg-info/dependency_links.txt
CLUSTER_SELECTION.egg-info/not-zip-safe
CLUSTER_SELECTION.egg-info/requires.txt
CLUSTER_SELECTION.egg-info/top_level.txt