Metadata-Version: 1.0
Name: CLUSTER-SELECTION
Version: 0.0.2
Summary: Learning setup
Home-page: https://github.com/vineetbiyani09/ML/tree/master/CLUSTER_SELECTION
Author: Vineet Biyani, Jash Bhatia, Yash Doshi, Sagarika Raje
Author-email: UNKNOWN
License: MIT
Platform: UNKNOWN
